Metadata-Version: 2.1
Name: vendia-utils-brian-mcnamara
Version: 0.1.1
Summary: Utilies to work with Vendia services
Home-page: https://github.com/brian-vendia/vendia-utils
License: Apache
Platform: UNKNOWN
Classifier: Intended Audience :: Developers
Classifier: Operating System :: OS Independent
Classifier: Programming Language :: Python :: 3.8
Requires-Python: >=3.8
Provides-Extra: testing
